Metadata-Version: 2.1
Name: libpythonpro-barthjr
Version: 0.2
Summary: Módulo criado dentro do curso Python Pro para exemplificar a construção de projetos Python no curso PyTools
Home-page: https://github.com/BarthJr/libpythonpro_barthjr
Author: Junior Barth
Author-email: juniior.barth@gmail.com
License:                     GNU AFFERO GENERAL PUBLIC LICENSE
